plotly_ecdf/__init__.py
plotly_ecdf/plotly_ecdf.py
plotly_ecdf-0.1.2.dist-info/AUTHORS.rst
plotly_ecdf-0.1.2.dist-info/LICENSE
plotly_ecdf-0.1.2.dist-info/METADATA
plotly_ecdf-0.1.2.dist-info/WHEEL
plotly_ecdf-0.1.2.dist-info/top_level.txt
plotly_ecdf-0.1.2.dist-info/RECORD
