Metadata-Version: 2.1
Name: plotly-ecdf
Version: 0.1.2
Summary: Enables plotting ECDF curves using Plotly with a similar API to Plotly Express
Home-page: https://github.com/benlindsay/plotly-ecdf
Author: Ben Lindsay
Author-email: benjlindsay@gmail.com
License: MIT license
Keywords: plotly-ecdf
Platform: UNKNOWN
Classifier: Development Status :: 2 - Pre-Alpha
Classifier: Intended Audience :: Developers
Classifier: License :: OSI Approved :: MIT License
Classifier: Natural Language :: English
Classifier: Programming Language :: Python :: 3
Classifier: Programming Language :: Python :: 3.7
Classifier: Programming Language :: Python :: 3.8
Requires-Python: >=3.7
Requires-Dist: pandas (>=1.0.0)
Requires-Dist: plotly (>=4.0.0)
